secret_gen/__init__.py
secret_gen/main.py
secret_gen-1.1.dist-info/METADATA
secret_gen-1.1.dist-info/WHEEL
secret_gen-1.1.dist-info/entry_points.txt
secret_gen-1.1.dist-info/top_level.txt
secret_gen-1.1.dist-info/RECORD
