Metadata-Version: 2.1
Name: secret-gen
Version: 1.1
Summary: Password generator
Author: Grumnik
Provides-Extra: test
Requires-Dist: black ; extra == 'test'
Requires-Dist: pylint ; extra == 'test'
